CHANGES.rst
CONTENT-ATTRIBUTIONS.rst
CONTRIBUTORS.rst
EUPL-1.2.txt
GNU-AGPL-3.0.txt
MANIFEST.in
README.rst
THIRD-PARTY-NOTICES.rst
licenses-backend.txt
licenses-frontend.txt
requirements-deploy.txt
requirements-docs.txt
requirements-release.txt
setup.cfg
setup.py
webpack.banner.txt
patzilla/__init__.py
patzilla/commands.py
patzilla/version.py
patzilla.egg-info/PKG-INFO
patzilla.egg-info/SOURCES.txt
patzilla.egg-info/dependency_links.txt
patzilla.egg-info/entry_points.txt
patzilla.egg-info/not-zip-safe
patzilla.egg-info/requires.txt
patzilla.egg-info/top_level.txt
patzilla/access/__init__.py
patzilla/access/drawing.py
patzilla/access/office.py
patzilla/access/cipo/__init__.py
patzilla/access/cipo/drawing.py
patzilla/access/depatech/__init__.py
patzilla/access/depatech/client.py
patzilla/access/depatech/clientpool.py
patzilla/access/depatech/expression.py
patzilla/access/depatech/expression.rst
patzilla/access/dpma/__init__.py
patzilla/access/dpma/depatisconnect.py
patzilla/access/dpma/depatisnet.py
patzilla/access/dpma/dpmaregister.py
patzilla/access/dpma/util.py
patzilla/access/epo/__init__.py
patzilla/access/epo/espacenet/__init__.py
patzilla/access/epo/espacenet/client.py
patzilla/access/epo/espacenet/pyramid.py
patzilla/access/epo/ops/__init__.py
patzilla/access/epo/ops/api.py
patzilla/access/epo/ops/client.py
patzilla/access/epo/ops/commands.py
patzilla/access/epo/ops/ops.rst
patzilla/access/epo/publicationserver/__init__.py
patzilla/access/epo/publicationserver/client.py
patzilla/access/generic/__init__.py
patzilla/access/generic/exceptions.py
patzilla/access/generic/pdf.py
patzilla/access/generic/search.py
patzilla/access/google/__init__.py
patzilla/access/google/search.py
patzilla/access/ificlaims/__init__.py
patzilla/access/ificlaims/api.py
patzilla/access/ificlaims/client.py
patzilla/access/ificlaims/clientpool.py
patzilla/access/ificlaims/commands.py
patzilla/access/ificlaims/expression.py
patzilla/access/ificlaims/expression.rst
patzilla/access/sip/__init__.py
patzilla/access/sip/client.py
patzilla/access/sip/clientpool.py
patzilla/access/sip/commands.py
patzilla/access/sip/concordance.py
patzilla/access/sip/expression.py
patzilla/access/sip/expression.rst
