Metadata-Version: 2.1
Name: patzilla
Version: 0.169.2
Summary: PatZilla is a modular patent information research platform and data integration toolkit. It features a modern user interface and access to multiple data sources.
Home-page: https://github.com/ip-tools/ip-navigator
Author: Andreas Motl
Author-email: andreas.motl@ip-tools.org
License: AGPL 3, EUPL 1.2
Keywords: patent information research management trademark design search fulltext patent patents patent-search patent-data information information-retrieval intellectual-property research researcher researchers research-data research-tool research-and-development epo-ops dpma uspto open-data opendata
Platform: UNKNOWN
Classifier: Development Status :: 5 - Production/Stable
Classifier: Environment :: Web Environment
Classifier: Framework :: Paste
Classifier: Framework :: Pyramid
Classifier: Intended Audience :: Developers
Classifier: Intended Audience :: Education
Classifier: Intended Audience :: End Users/Desktop
Classifier: Intended Audience :: Information Technology
Classifier: Intended Audience :: Legal Industry
Classifier: Intended Audience :: Manufacturing
Classifier: Intended Audience :: Science/Research
Classifier: License :: OSI Approved :: European Union Public Licence 1.2 (EUPL 1.2)
Classifier: License :: OSI Approved :: GNU Affero General Public License v3 or later (AGPLv3+)
Classifier: Natural Language :: English
Classifier: Operating System :: MacOS :: MacOS X
Classifier: Operating System :: POSIX :: Linux
Classifier: Programming Language :: JavaScript
Classifier: Programming Language :: Python
Classifier: Topic :: Internet :: WWW/HTTP
Classifier: Topic :: Internet :: WWW/HTTP :: WSGI :: Application
Classifier: Topic :: Scientific/Engineering
Provides-Extra: test
